overlap_integral/__init__.py
overlap_integral/overlap_integral.py
overlap_integral-0.1.8.dist-info/METADATA
overlap_integral-0.1.8.dist-info/WHEEL
overlap_integral-0.1.8.dist-info/RECORD
