Metadata-Version: 2.3
Name: overlap-integral
Version: 0.1.8
Summary: This package aims to compute the overlap integral between two probability density functions.
License: MIT
Author: Matheus Bacigalupo Kiataki
Author-email: kiatakimatheus@gmail.com
Requires-Python: >=3.12.3
Classifier: License :: OSI Approved :: MIT License
Classifier: Programming Language :: Python :: 3
Classifier: Programming Language :: Python :: 3.13
Requires-Dist: kaleido (==0.2.0)
Requires-Dist: numpy (>=1.21,<=3.0)
Requires-Dist: plotly (>=5.10.0,<=6.20.0)
Requires-Dist: pytest (>=8.1.1,<=8.4.0)
Requires-Dist: scipy (>=1.11.1,<=1.20)
Project-URL: Documentation, https://github.com/kiataki/overlap-integral/blob/main/README.md
Project-URL: Homepage, https://github.com/kiataki/
Project-URL: Repository, https://github.com/kiataki/overlap-integral
